flowstep/__init__.py
flowstep/defaults.py
flowstep/examples/__init__.py
flowstep/examples/examples.py
flowstep/examples/utils.py
flowstep/flow.py
flowstep/logging_.py
flowstep/utils.py
flowstep-0.0.1.dist-info/LICENSE
flowstep-0.0.1.dist-info/METADATA
flowstep-0.0.1.dist-info/WHEEL
flowstep-0.0.1.dist-info/RECORD
